egga/expression.py
egga/geometric_algebra.py
egga/utils.py
egga-0.1.9.dist-info/METADATA
egga-0.1.9.dist-info/WHEEL
egga-0.1.9.dist-info/RECORD
