Metadata-Version: 2.1
Name: egga
Version: 0.1.9
Summary: Symbolic Geometric Algebra with E-Graphs 
Home-page: https://github.com/RobinKa/egga
License: MIT
Keywords: geometric-algebra,clifford-algebra,simplification,equations,egraph,egglog,multi-vector,para-vector,mathematics
Author: Robin Kahlow
Author-email: tora@warlock.ai
Requires-Python: >=3.8,<4.0
Classifier: Development Status :: 3 - Alpha
Classifier: Intended Audience :: Developers
Classifier: Intended Audience :: Education
Classifier: Intended Audience :: Science/Research
Classifier: License :: OSI Approved :: MIT License
Classifier: Programming Language :: Python :: 3
Classifier: Programming Language :: Python :: 3.8
Classifier: Programming Language :: Python :: 3.9
Classifier: Programming Language :: Python :: 3.10
Classifier: Programming Language :: Python :: 3.11
Classifier: Programming Language :: Python :: 3 :: Only
Classifier: Topic :: Scientific/Engineering
Classifier: Topic :: Scientific/Engineering :: Mathematics
Classifier: Topic :: Scientific/Engineering :: Physics
Classifier: Topic :: Software Development
Classifier: Topic :: Software Development :: Libraries
Classifier: Topic :: Software Development :: Libraries :: Python Modules
Requires-Dist: egglog (>=0.7.0,<0.8.0)
Project-URL: Repository, https://github.com/RobinKa/egga
